mopidy_sevensegmentdisplay/__init__.py
mopidy_sevensegmentdisplay/actor.py
mopidy_sevensegmentdisplay/alert.py
mopidy_sevensegmentdisplay/animation.py
mopidy_sevensegmentdisplay/cava.config
mopidy_sevensegmentdisplay/clock.py
mopidy_sevensegmentdisplay/display.py
mopidy_sevensegmentdisplay/equalizer.py
mopidy_sevensegmentdisplay/ext.conf
mopidy_sevensegmentdisplay/gpio.py
mopidy_sevensegmentdisplay/http.py
mopidy_sevensegmentdisplay/ir.py
mopidy_sevensegmentdisplay/light_sensor.py
mopidy_sevensegmentdisplay/max7219.py
mopidy_sevensegmentdisplay/menu.py
mopidy_sevensegmentdisplay/mqtt.py
mopidy_sevensegmentdisplay/music.py
mopidy_sevensegmentdisplay/run.sh
mopidy_sevensegmentdisplay/threader.py
mopidy_sevensegmentdisplay/timer.py
mopidy_sevensegmentdisplay/worker.py
mopidy_sevensegmentdisplay/static/bootstrap-theme.css
mopidy_sevensegmentdisplay/static/bootstrap.css
mopidy_sevensegmentdisplay/static/bootstrap.js
mopidy_sevensegmentdisplay/static/jquery.js
mopidy_sevensegmentdisplay/static/theme.css
mopidy_sevensegmentdisplay/templates/base.html
mopidy_sevensegmentdisplay/templates/index.html
mopidy_sevensegmentdisplay-0.9.15.dist-info/licenses/LICENSE
mopidy_sevensegmentdisplay-0.9.15.dist-info/METADATA
mopidy_sevensegmentdisplay-0.9.15.dist-info/WHEEL
mopidy_sevensegmentdisplay-0.9.15.dist-info/entry_points.txt
mopidy_sevensegmentdisplay-0.9.15.dist-info/top_level.txt
mopidy_sevensegmentdisplay-0.9.15.dist-info/RECORD
