Metadata-Version: 2.4
Name: Mopidy-SevenSegmentDisplay
Version: 0.9.15
Summary: A Mopidy extension for using it with seven segment display.
Home-page: https://github.com/JumalIO/mopidy-sevensegmentdisplay
Author: Julius
Author-email: spamjulius@mail.com
Maintainer: Julius
Maintainer-email: spamjulius@mail.com
License: Apache License, Version 2.0
Classifier: Environment :: No Input/Output (Daemon)
Classifier: Intended Audience :: End Users/Desktop
Classifier: License :: OSI Approved :: Apache Software License
Classifier: Operating System :: OS Independent
Classifier: Programming Language :: Python :: 3
Classifier: Topic :: Multimedia :: Sound/Audio :: Players
Requires-Python: >= 3.7
License-File: LICENSE
Requires-Dist: setuptools
Requires-Dist: Mopidy>=3.0
Requires-Dist: Pykka>=1.1
Requires-Dist: monotonic>=1.4
Dynamic: author
Dynamic: author-email
Dynamic: classifier
Dynamic: description
Dynamic: description-content-type
Dynamic: home-page
Dynamic: license
Dynamic: license-file
Dynamic: maintainer
Dynamic: maintainer-email
Dynamic: requires-dist
Dynamic: requires-python
Dynamic: summary
